octopulse_logger/__init__.py
octopulse_logger/logger_setup.py
octopulse_logger-0.2.1.dist-info/LICENSE
octopulse_logger-0.2.1.dist-info/METADATA
octopulse_logger-0.2.1.dist-info/WHEEL
octopulse_logger-0.2.1.dist-info/top_level.txt
octopulse_logger-0.2.1.dist-info/RECORD
