Metadata-Version: 2.1
Name: octopulse-logger
Version: 0.2.1
Summary: A Python library to setup clean structured logs, for local development, and production with Google Cloud Logging.
Home-page: https://gitlab.com/octopulse/back/octopulse-python-logger
Author: Hugo Bauer
Author-email: hugo@octopulse.io
License: UNKNOWN
Project-URL: Bug Tracker, https://gitlab.com/octopulse/back/octopulse-python-logger/-/issues
Platform: UNKNOWN
Classifier: Programming Language :: Python :: 3
Classifier: License :: OSI Approved :: MIT License
Classifier: Operating System :: OS Independent
License-File: LICENSE
Requires-Dist: google-cloud-logging
Requires-Dist: python-json-logger
Requires-Dist: structlog
Requires-Dist: colorama
